Metadata-Version: 2.1
Name: tornado-fastrpc
Version: 1.0.1
Summary: Asynchronous XML-RPC and FastPRC client for Python's Tornado
Home-page: https://github.com/seznam/tornado-fastrpc
Author: Jan Seifert (Seznam.cz, a.s.)
Author-email: jan.seifert@firma.seznam.cz
License: commercial
Platform: any
Classifier: Operating System :: POSIX :: Linux
Classifier: Programming Language :: Python :: 2.7
Classifier: Programming Language :: Python :: 3.4
Classifier: Programming Language :: Python :: 3.5
Classifier: License :: OSI Approved :: BSD License
Classifier: Operating System :: OS Independent
Classifier: Development Status :: 3 - Alpha
Classifier: Environment :: Other Environment
Classifier: Intended Audience :: Developers
Classifier: Topic :: Software Development :: Libraries :: Python Modules
Provides-Extra: FastRPC
